{
  "type": "Feature",
  "properties": {
    "gn:admin1_code":"1.0",
    "gn:asciiname":"Nyonyane",
    "gn:country_code":"SZ",
    "gn:dem":394,
    "gn:feature_class":"P",
    "gn:feature_code":"PPL",
    "gn:name":"Nyonyane",
    "gn:population":0,
    "gn:timezone":"Africa/Mbabane",
    "iso:country":"SZ",
    "wof:name":"Nyonyane",
    "wof:placetype":"locality"
},
  "geometry": {"coordinates":[31.44916,-26.11405],"type":"Point"}
}