{
  "type": "Feature",
  "properties": {
    "gn:admin1_code":"4.0",
    "gn:asciiname":"Hluthi",
    "gn:country_code":"SZ",
    "gn:dem":682,
    "gn:feature_class":"P",
    "gn:feature_code":"PPL",
    "gn:name":"Hluthi",
    "gn:population":0,
    "gn:timezone":"Africa/Mbabane",
    "iso:country":"SZ",
    "name:pol_x_preferred":[
        "Hluthi"
    ],
    "wof:name":"Hluthi",
    "wof:placetype":"locality"
},
  "geometry": {"coordinates":[31.57,-27.21],"type":"Point"}
}