{
  "type": "Feature",
  "properties": {
    "gn:admin1_code":"0.0",
    "gn:asciiname":"Siphofaneni",
    "gn:cc2":"SZ",
    "gn:country_code":"SZ",
    "gn:dem":195,
    "gn:feature_class":"P",
    "gn:feature_code":"PPL",
    "gn:name":"Siphofaneni",
    "gn:population":0,
    "gn:timezone":"Africa/Mbabane",
    "iso:country":"SZ",
    "name:ceb_x_preferred":[
        "Siphofaneni"
    ],
    "name:deu_x_preferred":[
        "Siphofaneni"
    ],
    "name:fra_x_preferred":[
        "Siphofaneni"
    ],
    "name:ita_x_preferred":[
        "Inkhundla Siphofaneni"
    ],
    "name:pol_x_preferred":[
        "Siphofaneni"
    ],
    "name:rus_x_preferred":[
        "\u0421\u0438\u043f\u043e\u0444\u0430\u043d\u0435\u043d\u0438"
    ],
    "name:und_x_variant":[
        "Sipofanenibrug",
        "Sipofaneni Bridge",
        "Spofanene",
        "Sipofaneni",
        "Siphofaneni"
    ],
    "wof:name":"Siphofaneni",
    "wof:placetype":"locality"
},
  "geometry": {"coordinates":[31.68333,-26.68333],"type":"Point"}
}