{
  "type": "Feature",
  "properties": {
    "gn:admin1_code":"1.0",
    "gn:asciiname":"Rocklands",
    "gn:country_code":"SZ",
    "gn:dem":1048,
    "gn:feature_class":"P",
    "gn:feature_code":"PPL",
    "gn:name":"Rocklands",
    "gn:population":0,
    "gn:timezone":"Africa/Mbabane",
    "iso:country":"SZ",
    "name:ceb_x_preferred":[
        "Rocklands"
    ],
    "name:cym_x_preferred":[
        "Rocklands"
    ],
    "name:fas_x_preferred":[
        "\u0631\u0627\u06a9\u0644\u0646\u062f\u0632"
    ],
    "name:nld_x_preferred":[
        "Rocklands"
    ],
    "name:pol_x_preferred":[
        "Rocklands"
    ],
    "name:swe_x_preferred":[
        "Rocklands"
    ],
    "wof:name":"Rocklands",
    "wof:placetype":"locality"
},
  "geometry": {"coordinates":[31.28333,-25.95],"type":"Point"}
}