{
  "type": "Feature",
  "properties": {
    "gn:admin1_code":"0.0",
    "gn:asciiname":"Mooihoek",
    "gn:country_code":"SZ",
    "gn:dem":898,
    "gn:feature_class":"P",
    "gn:feature_code":"PPL",
    "gn:name":"Mooihoek",
    "gn:population":0,
    "gn:timezone":"Africa/Mbabane",
    "iso:country":"SZ",
    "wof:name":"Mooihoek",
    "wof:placetype":"locality"
},
  "geometry": {"coordinates":[31.46667,-26.96667],"type":"Point"}
}