{
  "type": "Feature",
  "properties": {
    "gn:admin1_code":"0.0",
    "gn:asciiname":"Abercorn",
    "gn:country_code":"SZ",
    "gn:dem":114,
    "gn:feature_class":"P",
    "gn:feature_code":"PPL",
    "gn:name":"Abercorn",
    "gn:population":0,
    "gn:timezone":"Africa/Mbabane",
    "iso:country":"SZ",
    "name:ang_x_preferred":[
        "Abercurnig"
    ],
    "name:deu_x_preferred":[
        "Abercorn"
    ],
    "name:eus_x_preferred":[
        "Abercorn"
    ],
    "name:fra_x_preferred":[
        "Abercorn"
    ],
    "name:gla_x_preferred":[
        "Obar Ch\u00f9irnidh"
    ],
    "name:gle_x_preferred":[
        "Obar Ch\u00fairnidh"
    ],
    "name:ita_x_preferred":[
        "Abercorn"
    ],
    "name:nld_x_preferred":[
        "Abercorn"
    ],
    "name:nno_x_preferred":[
        "Abercorn"
    ],
    "name:nor_x_preferred":[
        "Abercorn"
    ],
    "name:spa_x_preferred":[
        "Abercorn"
    ],
    "name:und_x_variant":[
        "Abercorn Pont",
        "Abercorn Point"
    ],
    "wof:name":"Abercorn",
    "wof:placetype":"locality"
},
  "geometry": {"coordinates":[32.13333,-26.83333],"type":"Point"}
}