{
  "type": "Feature",
  "properties": {
    "gn:admin1_code":"0.0",
    "gn:asciiname":"Abercorn",
    "gn:country_code":"SZ",
    "gn:dem":114,
    "gn:feature_class":"P",
    "gn:feature_code":"PPL",
    "gn:name":"Abercorn",
    "gn:population":0,
    "gn:timezone":"Africa/Mbabane",
    "iso:country":"SZ",
    "name:und_x_variant":[
        "Abercorn Pont",
        "Abercorn Point",
        "Abercorn"
    ],
    "wof:name":"Abercorn",
    "wof:placetype":"locality"
},
  "geometry": {"coordinates":[32.13333,-26.83333],"type":"Point"}
}