{
  "type": "Feature",
  "properties": {
    "gn:admin1_code":"3.0",
    "gn:asciiname":"Matsapha",
    "gn:cc2":"SZ",
    "gn:country_code":"SZ",
    "gn:dem":629,
    "gn:feature_class":"P",
    "gn:feature_code":"PPL",
    "gn:name":"Matsapha",
    "gn:population":0,
    "gn:timezone":"Africa/Mbabane",
    "iso:country":"SZ",
    "name:deu_x_preferred":[
        "Matsapha"
    ],
    "name:eng_x_preferred":[
        "Matsapha"
    ],
    "name:und_x_variant":[
        "Matapa",
        "Matsapa"
    ],
    "wof:name":"Matsapha",
    "wof:placetype":"locality"
},
  "geometry": {"coordinates":[31.30795,-26.50253],"type":"Point"}
}