{
  "type": "Feature",
  "properties": {
    "iso:country":"SZ",
    "name:afr_x_preferred":[
        "Golela"
    ],
    "name:ara_x_preferred":[
        "\u063a\u0648\u0644\u064a\u0644\u0627"
    ],
    "name:deu_x_preferred":[
        "EGolela"
    ],
    "name:eng_x_preferred":[
        "Golela"
    ],
    "name:nld_x_preferred":[
        "Golela"
    ],
    "name:nso_x_preferred":[
        "Golela"
    ],
    "name:por_x_preferred":[
        "Golela"
    ],
    "ne:ADM0CAP":0.0,
    "ne:ADM0NAME":"Swaziland",
    "ne:ADM0_A3":"SWZ",
    "ne:ADM1NAME":"Shiselweni",
    "ne:ADMIN1_COD":0,
    "ne:CAPALT":0,
    "ne:CHANGED":0,
    "ne:CHECKME":0,
    "ne:COMPARE":0,
    "ne:DIFFASCII":0,
    "ne:ELEVATION":0.0,
    "ne:FEATURECLA":"Populated place",
    "ne:GEONAMEID":-1,
    "ne:GN_POP":0,
    "ne:GTOPO30":0.0,
    "ne:ISO_A2":"SZ",
    "ne:LABELRANK":8,
    "ne:LATITUDE":-27.296178,
    "ne:LONGITUDE":31.900006,
    "ne:LS_MATCH":1,
    "ne:LS_NAME":"Golela",
    "ne:MAX_AREAKM":5.0,
    "ne:MAX_AREAMI":2.0,
    "ne:MAX_BBXMAX":31.9,
    "ne:MAX_BBXMIN":31.875,
    "ne:MAX_BBYMAX":-27.291667,
    "ne:MAX_BBYMIN":-27.325,
    "ne:MAX_NATSCA":20.0,
    "ne:MAX_PERKM":12.0,
    "ne:MAX_PERMI":8.0,
    "ne:MAX_POP10":3695,
    "ne:MAX_POP20":3695,
    "ne:MAX_POP300":0,
    "ne:MAX_POP310":0,
    "ne:MAX_POP50":0,
    "ne:MEAN_BBXC":31.8875,
    "ne:MEAN_BBYC":-27.309722,
    "ne:MEGACITY":0,
    "ne:MIN_AREAKM":5.0,
    "ne:MIN_AREAMI":2.0,
    "ne:MIN_BBXMAX":31.9,
    "ne:MIN_BBXMIN":31.875,
    "ne:MIN_BBYMAX":-27.291667,
    "ne:MIN_BBYMIN":-27.325,
    "ne:MIN_PERKM":12.0,
    "ne:MIN_PERMI":8.0,
    "ne:NAME":"Golela",
    "ne:NAMEASCII":"Golela",
    "ne:NAMEDIFF":0,
    "ne:NATSCALE":20,
    "ne:POP1950":0,
    "ne:POP1955":0,
    "ne:POP1960":0,
    "ne:POP1965":0,
    "ne:POP1970":0,
    "ne:POP1975":0,
    "ne:POP1980":0,
    "ne:POP1985":0,
    "ne:POP1990":0,
    "ne:POP1995":0,
    "ne:POP2000":0,
    "ne:POP2005":0,
    "ne:POP2010":0,
    "ne:POP2015":0,
    "ne:POP2020":0,
    "ne:POP2025":0,
    "ne:POP2050":0,
    "ne:POP_MAX":3695,
    "ne:POP_MIN":3695,
    "ne:POP_OTHER":0,
    "ne:RANK_MAX":4,
    "ne:RANK_MIN":4,
    "ne:SCALERANK":7,
    "ne:SOV0NAME":"Swaziland",
    "ne:SOV_A3":"SWZ",
    "ne:UN_FID":0,
    "ne:UN_LAT":0.0,
    "ne:UN_LONG":0.0,
    "ne:WORLDCITY":0,
    "ne:min_zoom":6.7,
    "wof:name":"Golela",
    "wof:placetype":"locality"
},
  "geometry": {"coordinates":[31.90000606153848,-27.2961775525016],"type":"Point"}
}