{
  "type": "Feature",
  "properties": {
    "gn:admin1_code":"2.0",
    "gn:asciiname":"Maphiveni",
    "gn:country_code":"SZ",
    "gn:dem":176,
    "gn:feature_class":"P",
    "gn:feature_code":"PPLL",
    "gn:name":"Maphiveni",
    "gn:population":0,
    "gn:timezone":"Africa/Mbabane",
    "iso:country":"SZ",
    "wof:name":"Maphiveni",
    "wof:placetype":"locality"
},
  "geometry": {"coordinates":[31.98841,-26.14126],"type":"Point"}
}