{
  "type": "Feature",
  "properties": {
    "gn:admin1_code":"0.0",
    "gn:asciiname":"Usutu",
    "gn:cc2":"SZ",
    "gn:country_code":"SZ",
    "gn:dem":670,
    "gn:feature_class":"P",
    "gn:feature_code":"PPL",
    "gn:name":"Usutu",
    "gn:population":0,
    "gn:timezone":"Africa/Mbabane",
    "iso:country":"SZ",
    "name:und_x_variant":[
        "Usutu Mission",
        "Usutu"
    ],
    "wof:name":"Usutu",
    "wof:placetype":"locality"
},
  "geometry": {"coordinates":[31.18333,-26.58333],"type":"Point"}
}