{
  "type": "Feature",
  "properties": {
    "gn:admin1_code":"0.0",
    "gn:asciiname":"Sicunusa",
    "gn:cc2":"SZ",
    "gn:country_code":"SZ",
    "gn:dem":1314,
    "gn:feature_class":"P",
    "gn:feature_code":"PPL",
    "gn:name":"Sicunusa",
    "gn:population":0,
    "gn:timezone":"Africa/Mbabane",
    "iso:country":"SZ",
    "name:pol_x_preferred":[
        "Sicunusa"
    ],
    "name:und_x_variant":[
        "Sigunusa",
        "Sicunusa"
    ],
    "wof:name":"Sicunusa",
    "wof:placetype":"locality"
},
  "geometry": {"coordinates":[30.95,-26.86667000000001],"type":"Point"}
}