{
  "type": "Feature",
  "properties": {
    "gn:admin1_code":"4.0",
    "gn:asciiname":"Mgazini",
    "gn:country_code":"SZ",
    "gn:dem":1197,
    "gn:feature_class":"P",
    "gn:feature_code":"PPL",
    "gn:name":"Mgazini",
    "gn:population":0,
    "gn:timezone":"Africa/Mbabane",
    "iso:country":"SZ",
    "wof:name":"Mgazini",
    "wof:placetype":"locality"
},
  "geometry": {"coordinates":[30.949,-26.796],"type":"Point"}
}