{
  "type": "Feature",
  "properties": {
    "iso:country":"SZ",
    "name:afr_x_preferred":[
        "Bulembu"
    ],
    "name:ceb_x_preferred":[
        "Bulembu"
    ],
    "name:deu_x_preferred":[
        "Bulembu"
    ],
    "name:eng_x_preferred":[
        "Bulembu"
    ],
    "name:nld_x_preferred":[
        "Bulembu"
    ],
    "name:por_x_preferred":[
        "Bulembu"
    ],
    "name:rus_x_preferred":[
        "\u0411\u0443\u043b\u0435\u043c\u0431\u0443"
    ],
    "name:und_x_variant":[
        "Compound"
    ],
    "qs:gn_country":"SZ",
    "qs:gn_fcode":"PPL",
    "qs:gn_pop":2260,
    "qs:name":"Bulembu",
    "qs:name_adm0":"Swaziland",
    "qs:name_adm1":"Hhohho",
    "qs:photos":175,
    "qs:photos_1k":35,
    "qs:photos_9k":1,
    "qs:photos_9r":4,
    "qs:photos_all":175,
    "qs:photos_sr":4,
    "qs:placetype":"Town",
    "qs:pop_sr":"4",
    "qs:woe_adm0":23424993,
    "wd:wordcount":632,
    "wof:name":"Bulembu",
    "wof:placetype":"locality",
    "wof:population":2260
},
  "geometry": {"coordinates":[31.13333,-25.96667],"type":"Point"}
}