{
  "type": "Feature",
  "properties": {
    "gn:country":"SZ",
    "gn:fcode":"PPL",
    "gn:population":1899,
    "iso:country":"SZ",
    "name:ceb_x_preferred":[
        "Tshaneni"
    ],
    "name:deu_x_preferred":[
        "Tshaneni"
    ],
    "name:eng_x_preferred":[
        "Tshaneni"
    ],
    "name:fra_x_preferred":[
        "Tshaneni"
    ],
    "name:nld_x_preferred":[
        "Tshaneni"
    ],
    "name:por_x_preferred":[
        "Tjaneni"
    ],
    "name:und_x_variant":[
        "Tahaneni"
    ],
    "name:vie_x_preferred":[
        "Tshaneni"
    ],
    "qs:name":"Tshaneni",
    "qs:photos_9r":0,
    "qs:photos_sr":0,
    "qs:pop_sr":"3",
    "wd:wordcount":111,
    "wof:name":"Tshaneni",
    "wof:placetype":"locality",
    "wof:population":1899
},
  "geometry": {"coordinates":[31.71667,-25.98333],"type":"Point"}
}