{
  "type": "Feature",
  "properties": {
    "gn:country":"SZ",
    "gn:fcode":"PPL",
    "gn:population":2000,
    "iso:country":"SZ",
    "name:afr_x_preferred":[
        "Lavumisa"
    ],
    "name:ast_x_preferred":[
        "Lavumisa"
    ],
    "name:bul_x_preferred":[
        "\u041b\u0430\u0432\u0443\u043c\u0438\u0441\u0430"
    ],
    "name:cat_x_preferred":[
        "Lavumisa"
    ],
    "name:ceb_x_preferred":[
        "Lavumisa"
    ],
    "name:deu_x_preferred":[
        "Lavumisa"
    ],
    "name:eng_x_preferred":[
        "Lavumisa"
    ],
    "name:fin_x_preferred":[
        "Lavumisa"
    ],
    "name:fra_x_preferred":[
        "Lavumisa"
    ],
    "name:ita_x_preferred":[
        "Lavumisa"
    ],
    "name:jpn_x_preferred":[
        "\u30e9\u30d6\u30df\u30b5"
    ],
    "name:nld_x_preferred":[
        "Lavumisa"
    ],
    "name:pol_x_preferred":[
        "Lavumisa"
    ],
    "name:por_x_preferred":[
        "Lavumisa"
    ],
    "name:ron_x_preferred":[
        "Lavumisa"
    ],
    "name:und_x_variant":[
        "Gollel"
    ],
    "name:zho_x_preferred":[
        "\u62c9\u6b66\u7c73\u85a9"
    ],
    "name:zul_x_preferred":[
        "ILavumisa"
    ],
    "qs_pg:aaroncc":"SZ",
    "qs_pg:gn_country":"SZ",
    "qs_pg:gn_fcode":"PPL",
    "qs_pg:gn_pop":2000,
    "qs_pg:name":"Lavumisa",
    "qs_pg:photos_9r":0,
    "qs_pg:photos_sr":0,
    "qs_pg:pop_sr":3,
    "qs_pg:qs_pg_placetype":"locality",
    "wof:name":"Lavumisa",
    "wof:placetype":"locality",
    "wof:population":2000
},
  "geometry": {"coordinates":[31.89198,-27.31005],"type":"Point"}
}