{
  "type": "Feature",
  "properties": {
    "gn:country":"SZ",
    "gn:fcode":"PPL",
    "gn:population":1281,
    "iso:country":"SZ",
    "name:und_x_variant":[
        "Darktown"
    ],
    "qs_pg:aaroncc":"SZ",
    "qs_pg:gn_country":"SZ",
    "qs_pg:gn_fcode":"PPL",
    "qs_pg:gn_pop":1281,
    "qs_pg:name":"Darkton",
    "qs_pg:photos_9r":0,
    "qs_pg:photos_sr":0,
    "qs_pg:pop_sr":3,
    "qs_pg:qs_pg_placetype":"locality",
    "wof:name":"Darkton",
    "wof:placetype":"locality",
    "wof:population":1281
},
  "geometry": {"coordinates":[31.03333,-26.23333],"type":"Point"}
}