{
  "type": "Feature",
  "properties": {
    "gn:admin1_code":"2.0",
    "gn:asciiname":"Mpaka",
    "gn:country_code":"SZ",
    "gn:dem":322,
    "gn:feature_class":"P",
    "gn:feature_code":"PPL",
    "gn:name":"Mpaka",
    "gn:population":0,
    "gn:timezone":"Africa/Mbabane",
    "iso:country":"SZ",
    "name:deu_x_preferred":[
        "Mpaka"
    ],
    "name:nld_x_preferred":[
        "Mpaka"
    ],
    "name:por_x_preferred":[
        "Mpaka"
    ],
    "name:rus_x_preferred":[
        "\u041c\u043f\u0430\u043a\u0430"
    ],
    "wof:name":"Mpaka",
    "wof:placetype":"locality"
},
  "geometry": {"coordinates":[31.78,-26.412],"type":"Point"}
}