{
  "type": "Feature",
  "properties": {
    "gn:admin1_code":"3.0",
    "gn:asciiname":"Mafutseni",
    "gn:country_code":"SZ",
    "gn:dem":507,
    "gn:feature_class":"P",
    "gn:feature_code":"PPL",
    "gn:name":"Mafutseni",
    "gn:population":0,
    "gn:timezone":"Africa/Mbabane",
    "iso:country":"SZ",
    "name:ceb_x_preferred":[
        "Mafutseni"
    ],
    "name:deu_x_preferred":[
        "Mafutseni"
    ],
    "name:ita_x_preferred":[
        "Inkhundla Mafutseni"
    ],
    "name:pol_x_preferred":[
        "Mafutseni"
    ],
    "name:ukr_x_preferred":[
        "\u041c\u0430\u0444\u0443\u0442\u0441\u0435\u043d\u0456"
    ],
    "wof:name":"Mafutseni",
    "wof:placetype":"locality"
},
  "geometry": {"coordinates":[31.52,-26.44],"type":"Point"}
}